hairgap_binaries/__init__.py
hairgap_binaries/linux-x86_64-hairgapr
hairgap_binaries/linux-x86_64-hairgaps
hairgap_binaries/test_hairgap_binaries.py
hairgap_binaries-1.1.0.dist-info/LICENSE
hairgap_binaries-1.1.0.dist-info/METADATA
hairgap_binaries-1.1.0.dist-info/WHEEL
hairgap_binaries-1.1.0.dist-info/RECORD
